{"cameraMode":{"drawMode":0,"name":"Shaded","section":"Shading Mode"},"sceneLighting":true,"audioPlay":false,"sceneViewState":{"showFog":true,"showMaterialUpdate":false,"showSkybox":true,"showFlares":true,"showImageEffects":true,"showParticleSystems":true,"showVisualEffectGraphs":true,"m_FxEnabled":false},"in2DMode":false,"pivot":{"x":1.8887710571289063,"y":7.869087219238281,"z":-16.991943359375},"rotation":{"x":-0.09984465688467026,"y":0.8980363607406616,"z":-0.3337337374687195,"w":-0.26866939663887026},"size":76.25653076171875,"orthographic":false}