{"cameraMode":{"drawMode":0,"name":"Shaded","section":"Shading Mode"},"sceneLighting":true,"audioPlay":false,"sceneViewState":{"showFog":true,"showMaterialUpdate":false,"showSkybox":true,"showFlares":true,"showImageEffects":true,"showParticleSystems":true,"showVisualEffectGraphs":true,"m_FxEnabled":false},"in2DMode":false,"pivot":{"x":-18.5643367767334,"y":-0.5293064117431641,"z":-6.5166015625},"rotation":{"x":-0.13233354687690736,"y":-0.6163011789321899,"z":0.10605499148368836,"w":-0.7690408229827881},"size":4.389211654663086,"orthographic":false}